pyGLV/__init__.py
pyGLV/_version.py
pyGLV/GL/Scene.py
pyGLV/GL/Shader.py
pyGLV/GL/SimpleCamera.py
pyGLV/GL/VertexArray.py
pyGLV/GL/__init__.py
pyGLV/GL/normals.py
pyGLV/GL/obj_to_mesh.py
pyGLV/GL/terrain.py
pyGLV/GUI/Viewer.py
pyGLV/GUI/__init__.py
pyGLV/examples/__init__.py
pyGLV/examples/example_1_empty_window.py
pyGLV/examples/example_2_empty_window_with_GUI.py
pyGLV/examples/example_3_cube_lookAt.py
pyGLV/examples/example_4_cube_axes_terrain.py
pyGLV/examples/example_5_lights_cube.py
pyGLV/examples/example_6_import_objects.py
pyGLV/examples/example_7_cameraSystem.py
pyGLV/tests/__init__.py
pyGLV/tests/test_Event.py
pyGLV/tests/test_Scene.py
pyGLV/tests/test_Shader.py
pyGLV/tests/test_VertexArray.py
pyGLV/tests/test_Viewer.py
pyGLV-1.0.5.dist-info/LICENSE.txt
pyGLV-1.0.5.dist-info/METADATA
pyGLV-1.0.5.dist-info/WHEEL
pyGLV-1.0.5.dist-info/top_level.txt
pyGLV-1.0.5.dist-info/RECORD
