Metadata-Version: 2.1
Name: pyGLV
Version: 1.0.5
Summary: pyGLV (computer Graphics for deep Learning and scientific Visualization)
Home-page: https://github.com/papagiannakis/pyGLV
Author: George Papagiannakis
Author-email: papagian@csd.uoc.gr
Maintainer: Manos Kamarianakis
Maintainer-email: m.kamarianakis@gmail.com
License: Apache 2
Project-URL: Homepage, https://github.com/papagiannakis/pyGLV
Project-URL: Documentation, https://pyglv.readthedocs.io
Keywords: ECS,Scenegraph,Python design patterns,Computer Graphics
Classifier: License :: OSI Approved :: Apache Software License
Classifier: Environment :: MacOS X
Classifier: Environment :: Win32 (MS Windows)
Classifier: Environment :: X11 Applications
Classifier: Operating System :: Microsoft :: Windows
Classifier: Operating System :: MacOS
Classifier: Operating System :: Unix
Classifier: Programming Language :: Python :: 3.8
Classifier: Programming Language :: Python :: 3.9
Requires-Python: >=3.8,<3.10
License-File: LICENSE.txt
Requires-Dist: pip
Requires-Dist: setuptools (>=61)
Requires-Dist: wheel
Requires-Dist: numpy
Requires-Dist: scipy
Requires-Dist: pyECSS
Requires-Dist: imgui
Requires-Dist: PyOpenGL
Requires-Dist: PyOpenGL-accelerate
Requires-Dist: pysdl2
Requires-Dist: pysdl2-dll
Requires-Dist: ipykernel
